{
	"credit": "Made with Blockbench",
	"textures": {
		"0": "adventurecraft:blocks/brown_mushroom_stalk",
		"2": "adventurecraft:blocks/brown_mushroom_cap2",
		"3": "adventurecraft:blocks/brown_mushroom_cap1",
		"5": "adventurecraft:blocks/brown_mushroom_cap3",
		"particle": "adventurecraft:blocks/brown_mushroom_stalk"
	},
	"elements": [
		{
			"from": [2.43, -0.375, 4],
			"to": [3.63, 1.575, 5.2],
			"faces": {
				"north": {"uv": [0, 0, 16, 15.625], "texture": "#0"},
				"east": {"uv": [0, 0, 16, 15.625], "texture": "#0"},
				"south": {"uv": [0, 0, 16, 15.625], "texture": "#0"},
				"west": {"uv": [0, 0, 16, 15.625], "texture": "#0"}
			}
		},
		{
			"from": [1.83, 1.575, 3.4],
			"to": [4.23, 2.175, 5.8],
			"faces": {
				"north": {"uv": [0, 0, 13, 7.5], "texture": "#2"},
				"east": {"uv": [0, 0, 15, 7.5], "texture": "#2"},
				"south": {"uv": [0, 0, 16, 8.5], "texture": "#2"},
				"west": {"uv": [0, 0, 15, 7.5], "texture": "#2"},
				"up": {"uv": [0, 0, 16, 15], "rotation": 90, "texture": "#2"}
			}
		},
		{
			"from": [2.13, 1.875, 3.7],
			"to": [3.93, 2.475, 5.5],
			"faces": {
				"north": {"uv": [0, 0, 13, 7.5], "texture": "#2"},
				"east": {"uv": [0, 4, 16, 10.5], "texture": "#2"},
				"south": {"uv": [0, 0, 15, 6.5], "texture": "#2"},
				"west": {"uv": [0, 0, 13, 6.5], "texture": "#2"},
				"up": {"uv": [0, 0, 16, 16], "rotation": 90, "texture": "#5"}
			}
		},
		{
			"from": [-4.92931, 3.92142, 4.615],
			"to": [-3.87931, 6.05142, 5.815],
			"rotation": {"angle": 22.5, "axis": "z", "origin": [8, 8, 8]},
			"faces": {
				"north": {"uv": [0, 0, 15.875, 15.775], "texture": "#0"},
				"east": {"uv": [0, 0, 16, 15.775], "texture": "#0"},
				"south": {"uv": [0, 0, 15.875, 15.775], "texture": "#0"},
				"west": {"uv": [0, 0, 16, 15.775], "texture": "#0"}
			}
		},
		{
			"from": [-5.44087, 5.96802, 4.195],
			"to": [-3.40087, 6.56802, 6.235],
			"rotation": {"angle": 22.5, "axis": "z", "origin": [8, 8, 8]},
			"faces": {
				"north": {"uv": [0, 0, 14, 7.5], "texture": "#2"},
				"east": {"uv": [0, 0, 13, 7.5], "texture": "#2"},
				"south": {"uv": [0, 0, 15, 5.5], "texture": "#2"},
				"west": {"uv": [0, 0, 16, 6.5], "texture": "#2"},
				"up": {"uv": [0, 0, 13, 13], "rotation": 90, "texture": "#2"}
			}
		},
		{
			"from": [-5.24754, 6.42747, 4.435],
			"to": [-3.68754, 6.81747, 5.995],
			"rotation": {"angle": 22.5, "axis": "z", "origin": [8, 8, 8]},
			"faces": {
				"north": {"uv": [0, 0, 13, 6.5], "texture": "#2"},
				"east": {"uv": [0, 0, 12, 5.5], "texture": "#2"},
				"south": {"uv": [0, 0, 14, 5.5], "texture": "#2"},
				"west": {"uv": [0, 0, 16, 7.5], "texture": "#2"},
				"up": {"uv": [0, 0, 16, 16], "rotation": 90, "texture": "#5"}
			}
		},
		{
			"from": [-0.71, 1.1252, 0.25506],
			"to": [0.49, 4.1852, 1.45506],
			"rotation": {"angle": -22.5, "axis": "x", "origin": [8, 8, 8]},
			"faces": {
				"north": {"uv": [16, 0, 0, 15.55], "texture": "#0"},
				"east": {"uv": [16, 0, 0, 15.55], "texture": "#0"},
				"south": {"uv": [16, 0, 0, 15.55], "texture": "#0"},
				"west": {"uv": [16, 0, 0, 15.55], "texture": "#0"}
			}
		},
		{
			"from": [-0.71, 1.50872, 2.3137],
			"to": [0.49, 3.66872, 3.4837],
			"faces": {
				"north": {"uv": [16, 0, 0, 15.8], "texture": "#0"},
				"east": {"uv": [15.975, 0, 0, 15.8], "texture": "#0"},
				"south": {"uv": [16, 0, 0, 15.8], "texture": "#0"},
				"west": {"uv": [15.975, 0, 0, 15.8], "texture": "#0"}
			}
		},
		{
			"from": [-1.31, 3.31, 1.805],
			"to": [1.09, 3.91, 4.205],
			"faces": {
				"north": {"uv": [14, 5, 2, 11.5], "texture": "#2"},
				"east": {"uv": [12, 0, 0, 7.5], "texture": "#2"},
				"south": {"uv": [14, 0, 0, 7.5], "texture": "#2"},
				"west": {"uv": [13, 7, 1, 13.5], "texture": "#2"},
				"up": {"uv": [16, 0, 0, 15], "rotation": 90, "texture": "#2"}
			}
		},
		{
			"from": [-1.01, 3.58, 2.135],
			"to": [0.79, 4.18, 3.935],
			"faces": {
				"north": {"uv": [12, 0, 0, 6.5], "texture": "#2"},
				"east": {"uv": [15, 0, 0, 6.5], "texture": "#2"},
				"south": {"uv": [14, 0, 0, 7.5], "texture": "#2"},
				"west": {"uv": [16, 10, 2, 15.5], "texture": "#2"},
				"up": {"uv": [16, 0, 0, 16], "rotation": 90, "texture": "#5"}
			}
		},
		{
			"from": [3.83, -0.315, 6.53],
			"to": [4.67, 1.215, 7.22],
			"faces": {
				"north": {"uv": [0, 0, 15.7, 15.275], "texture": "#0"},
				"east": {"uv": [0, 0, 15.575, 15.275], "texture": "#0"},
				"south": {"uv": [0, 0, 15.7, 15.275], "texture": "#0"},
				"west": {"uv": [0, 0, 15.575, 15.275], "texture": "#0"}
			}
		},
		{
			"from": [3.5, 1.005, 6.11],
			"to": [5.03, 1.395, 7.61],
			"faces": {
				"north": {"uv": [0, 0, 12.274, 7.325], "texture": "#2"},
				"east": {"uv": [0, 0, 11.25, 5.325], "texture": "#2"},
				"south": {"uv": [0, 0, 11.274, 5.325], "texture": "#2"},
				"west": {"uv": [0, 0, 12.25, 5.325], "texture": "#2"},
				"up": {"uv": [0, 0, 14.25, 11.274], "rotation": 90, "texture": "#2"}
			}
		},
		{
			"from": [3.68, 1.155, 6.26],
			"to": [4.88, 1.725, 7.4],
			"faces": {
				"north": {"uv": [0, 0, 13, 5.475], "texture": "#2"},
				"east": {"uv": [0, 0, 11.95, 4.475], "texture": "#2"},
				"south": {"uv": [0, 0, 16, 6.475], "texture": "#2"},
				"west": {"uv": [0, 0, 13.95, 7.475], "texture": "#2"},
				"up": {"uv": [3, 3, 12.95, 13], "rotation": 90, "texture": "#3"}
			}
		},
		{
			"from": [-0.79, -0.05, 0.47],
			"to": [0.05, 1.48, 1.16],
			"faces": {
				"north": {"uv": [0, 0, 15.7, 15.275], "texture": "#0"},
				"east": {"uv": [0, 0, 15.575, 15.275], "texture": "#0"},
				"south": {"uv": [0, 0, 15.7, 15.275], "texture": "#0"},
				"west": {"uv": [0, 0, 15.575, 15.275], "texture": "#0"}
			}
		},
		{
			"from": [-1.12, 1.27, 0.05],
			"to": [0.41, 1.66, 1.55],
			"faces": {
				"north": {"uv": [0, 0, 14.274, 5.325], "texture": "#2"},
				"east": {"uv": [0, 0, 12.25, 5.325], "texture": "#2"},
				"south": {"uv": [0, 0, 11.274, 5.325], "texture": "#2"},
				"west": {"uv": [0, 0, 15.25, 6.325], "texture": "#2"},
				"up": {"uv": [0, 0, 15.25, 13.274], "rotation": 90, "texture": "#2"}
			}
		},
		{
			"from": [-0.94, 1.42, 0.2],
			"to": [0.26, 1.99, 1.34],
			"faces": {
				"north": {"uv": [0, 0, 14, 4.475], "texture": "#2"},
				"east": {"uv": [0, 0, 11.95, 6.475], "texture": "#2"},
				"south": {"uv": [1, 8, 14, 15.475], "texture": "#2"},
				"west": {"uv": [0, 0, 13.95, 5.475], "texture": "#2"},
				"up": {"uv": [3, 3, 12.95, 13], "rotation": 90, "texture": "#3"}
			}
		},
		{
			"from": [2.1018, -1.2749, -1.6712],
			"to": [3.3282, 0.9589, -0.6638],
			"faces": {
				"north": {"uv": [0, 0, 15.7, 15.275], "texture": "#0"},
				"east": {"uv": [0, 0, 15.575, 15.275], "texture": "#0"},
				"south": {"uv": [0, 0, 15.7, 15.275], "texture": "#0"},
				"west": {"uv": [0, 0, 15.575, 15.275], "texture": "#0"}
			}
		},
		{
			"from": [1.62, 0.6523, -2.2844],
			"to": [3.8538, 1.2217, -0.0944],
			"faces": {
				"north": {"uv": [0, 0, 11.274, 4.325], "texture": "#2"},
				"east": {"uv": [0, 0, 12.25, 7.325], "texture": "#2"},
				"west": {"uv": [0, 0, 11.25, 5.325], "texture": "#2"},
				"up": {"uv": [0, 0, 15.25, 12.274], "rotation": 90, "texture": "#2"}
			}
		},
		{
			"from": [1.8828, 0.8713, -2.0654],
			"to": [3.6348, 1.7035, -0.401],
			"faces": {
				"north": {"uv": [0, 0, 8, 4.475], "texture": "#2"},
				"east": {"uv": [0, 0, 13.95, 7.475], "texture": "#2"},
				"west": {"uv": [0, 0, 11.95, 4.475], "texture": "#2"},
				"up": {"uv": [3, 3, 12.95, 13], "rotation": 90, "texture": "#3"}
			}
		},
		{
			"from": [6.12731, -1.56313, 0.3996],
			"to": [7.66031, 1.54667, 2.1516],
			"rotation": {"angle": -22.5, "axis": "z", "origin": [8, 8, 8]},
			"faces": {
				"north": {"uv": [0, 0, 15.875, 15.775], "texture": "#0"},
				"east": {"uv": [0, 0, 16, 15.775], "texture": "#0"},
				"south": {"uv": [-0.125, 0, 15.75, 15.775], "texture": "#0"},
				"west": {"uv": [0, 0, 16, 15.775], "texture": "#0"}
			}
		},
		{
			"from": [5.42877, 1.42491, -0.2136],
			"to": [8.40717, 2.30091, 2.7648],
			"rotation": {"angle": -22.5, "axis": "z", "origin": [8, 8, 8]},
			"faces": {
				"north": {"uv": [14, 0, 0, 6.5], "texture": "#2"},
				"east": {"uv": [16, 0, 0, 5.5], "texture": "#2"},
				"south": {"uv": [16, 0, 0, 4.5], "texture": "#2"},
				"west": {"uv": [14, 0, 0, 6.5], "texture": "#2"},
				"up": {"uv": [0, 16, 16, 0], "rotation": 90, "texture": "#2"}
			}
		},
		{
			"from": [5.84732, 2.0957, 0.1368],
			"to": [8.12492, 2.6651, 2.4144],
			"rotation": {"angle": -22.5, "axis": "z", "origin": [8, 8, 8]},
			"faces": {
				"north": {"uv": [13, 0, 0, 5.5], "texture": "#2"},
				"east": {"uv": [12, 0, 0, 4.5], "texture": "#2"},
				"south": {"uv": [13, 0, 0, 5.5], "texture": "#2"},
				"west": {"uv": [13, 0, 0, 5.5], "texture": "#2"},
				"up": {"uv": [0, 16, 16, 0], "rotation": 90, "texture": "#5"}
			}
		},
		{
			"from": [0.18173, -0.62119, 9.77594],
			"to": [1.65341, 1.99104, 11.06366],
			"rotation": {"angle": 22.5, "axis": "x", "origin": [8, 8, 8]},
			"faces": {
				"north": {"uv": [0, 0, 16, 15.775], "texture": "#0"},
				"east": {"uv": [0, 0, 15.875, 15.775], "texture": "#0"},
				"south": {"uv": [0, 0, 16, 15.775], "texture": "#0"},
				"west": {"uv": [0, 0, 15.875, 15.775], "texture": "#0"}
			}
		},
		{
			"from": [-0.33336, 1.88877, 9.18918],
			"to": [2.1685, 2.62461, 11.69103],
			"rotation": {"angle": 22.5, "axis": "x", "origin": [8, 8, 8]},
			"faces": {
				"north": {"uv": [0, 0, 13, 7.5], "texture": "#2"},
				"east": {"uv": [0, 0, 13, 6.5], "texture": "#2"},
				"south": {"uv": [2, 2, 15, 8.5], "texture": "#2"},
				"west": {"uv": [2, 7, 14, 13.5], "texture": "#2"},
				"up": {"uv": [0, 0, 15, 12], "texture": "#2"}
			}
		},
		{
			"from": [-0.03902, 2.45223, 9.54076],
			"to": [1.87416, 2.93053, 11.45394],
			"rotation": {"angle": 22.5, "axis": "x", "origin": [8, 8, 8]},
			"faces": {
				"north": {"uv": [0, 0, 15, 4.5], "texture": "#2"},
				"east": {"uv": [0, 0, 12, 3.5], "texture": "#2"},
				"south": {"uv": [0, 0, 13, 4.5], "texture": "#2"},
				"west": {"uv": [0, 0, 14, 4.5], "texture": "#2"},
				"up": {"uv": [0, 0, 16, 16], "texture": "#5"}
			}
		}
	],
	"display": {
		"thirdperson_righthand": {
			"rotation": [60, -64, 0],
			"translation": [0, 0, 5],
			"scale": [0.56, 0.52, 0.61]
		},
		"firstperson_righthand": {
			"rotation": [0, -55, -13],
			"translation": [6, 5, 1.5],
			"scale": [0.8, 0.8, 0.8]
		},
		"ground": {
			"translation": [4.5, 4.75, 3.75]
		},
		"gui": {
			"rotation": [18, 27, 0],
			"translation": [9, 5.5, 0],
			"scale": [1.1, 1.1, 1.1]
		}
	},
	"groups": [
		{
			"name": "group",
			"origin": [8, 8, 8],
			"children": [
				{
					"name": "1",
					"origin": [8, 8, 8],
					"children": [0, 1, 2]
				},
				{
					"name": "3",
					"origin": [8, 8, 8],
					"children": [3, 4, 5]
				},
				{
					"name": "4",
					"origin": [8, 8, 8],
					"children": [6, 7, 8, 9]
				},
				{
					"name": "5",
					"origin": [8, 8, 8],
					"children": [10, 11, 12]
				},
				{
					"name": "7",
					"origin": [8, 8, 8],
					"children": [13, 14, 15]
				},
				{
					"name": "5",
					"origin": [8, 8, 8],
					"children": [16, 17, 18]
				},
				{
					"name": "8",
					"origin": [8, 8, 8],
					"children": [19, 20, 21]
				},
				{
					"name": "6",
					"origin": [8, 8, 8],
					"children": [22, 23, 24]
				}
			]
		}
	]
}